{
  "$schema": "http://cyclonedx.org/schema/bom-1.6.schema.json",
  "bomFormat": "CycloneDX",
  "specVersion": "1.6",
  "version": 1,
  "metadata": {
    "timestamp": "2025-08-08T20:39:57+00:00",
    "lifecycles": [
      {
        "phase": "pre-build"
      }
    ],
    "authors": [
      {
        "bom-ref": "KimRyan",
        "name": "Kim Ryan"
      }
    ],
    "component": {
      "type": "library",
      "mime-type": "text/plain",
      "bom-ref": "pkg:raku/zef:kimryan/Lingua::EN::Fathom@0.0.1",
      "authors": [
        {
          "bom-ref": "KimRyan",
          "name": "Kim Ryan"
        }
      ],
      "publisher": "zef",
      "group": "zef:kimryan",
      "name": "Lingua::EN::Fathom",
      "version": "0.0.1",
      "description": "Measure readability of English text",
      "scope": "required",
      "hashes": [
        {
          "alg": "MD5",
          "content": "61dee8128fe74fc695b6e923c81c5e00"
        },
        {
          "alg": "SHA-1",
          "content": "2da6f23bb00f471e25b6248a2bd56a4371f28123"
        },
        {
          "alg": "SHA-256",
          "content": "7cc672cffd3fedcf2a2f7f83cd470ffd3e19a366a12ea1608f2e9e42016cb85b"
        },
        {
          "alg": "SHA-384",
          "content": "f60c3d0dcb71e4d5e869d2ed58a87716d1ad0b364ada2fc05bb5048e4ed6d5d16e477e6ce0471e35c20f4f1453a32a06"
        },
        {
          "alg": "SHA-512",
          "content": "c5129a571d816c1a818c9bb1e1fd044067db5a2b4420726faf739c6613e1e94a99381b2d3f23574809c9ab64414bef3f3bf6b2e3860d023c37476c546b46dfdf"
        }
      ],
      "licenses": [
        {
          "license": {
            "id": "Artistic-2.0",
            "acknowledgement": "declared",
            "url": "https://spdx.org/licenses/Artistic-2.0.json"
          }
        }
      ],
      "purl": "pkg:raku/zef:kimryan/Lingua::EN::Fathom@0.0.1",
      "externalReferences": [
        {
          "url": "git://github.com/kimryan/raku-Lingua-EN-Fathom",
          "type": "distribution"
        },
        {
          "url": "https://raku.land/zef:kimryan/Lingua::EN::Fathom?v=0.0.1",
          "type": "documentation"
        },
        {
          "url": "https://spdx.org/licenses/Artistic-2.0.json",
          "type": "license"
        }
      ],
      "tags": [
        "NLP",
        "TEXT"
      ]
    },
    "licenses": [
      {
        "license": {
          "id": "Artistic-2.0",
          "acknowledgement": "declared",
          "url": "https://spdx.org/licenses/Artistic-2.0.json"
        }
      }
    ],
    "tools": {
      "components": [
        {
          "type": "library",
          "mime-type": "text/plain",
          "bom-ref": "pkg:raku/zef:lizmat/SBOM::Raku@0.0.10",
          "authors": [
            {
              "bom-ref": "ElizabethMattijsen",
              "name": "Elizabeth Mattijsen"
            }
          ],
          "publisher": "zef",
          "group": "zef:lizmat",
          "name": "SBOM::Raku",
          "version": "0.0.10",
          "description": "Raku specific SBOM functionality",
          "scope": "required",
          "licenses": [
            {
              "license": {
                "id": "Artistic-2.0",
                "acknowledgement": "declared",
                "url": "https://spdx.org/licenses/Artistic-2.0.json"
              }
            }
          ],
          "purl": "pkg:raku/zef:lizmat/SBOM::Raku@0.0.10",
          "externalReferences": [
            {
              "url": "https://github.com/lizmat/SBOM-Raku",
              "type": "distribution"
            },
            {
              "url": "https://raku.land/zef:lizmat/SBOM::Raku?v=0.0.10",
              "type": "documentation"
            },
            {
              "url": "https://github.com/lizmat/SBOM-Raku/issues",
              "type": "issue-tracker"
            },
            {
              "url": "https://spdx.org/licenses/Artistic-2.0.json",
              "type": "license"
            },
            {
              "url": "https://github.com/lizmat/SBOM-Raku/archive/refs/tags/0.0.10.zip",
              "type": "source-distribution"
            },
            {
              "url": "mailto:liz@raku.rocks",
              "type": "support"
            }
          ],
          "tags": [
            "SBOM",
            "RAKU",
            "META"
          ]
        }
      ]
    }
  },
  "components": [
    {
      "type": "platform",
      "bom-ref": "Rakudo",
      "authors": [
        {
          "bom-ref": "RakudoCoreDevelopers",
          "name": "Rakudo Core Developers"
        }
      ],
      "publisher": "Rakudo Core Developers",
      "group": "Rakudo Core Developers",
      "name": "Rakudo",
      "version": "2025.06.1-12-g3aea31ed1",
      "description": "The Rakudo™ Compiler implementing the Raku® Programming Language",
      "scope": "required",
      "licenses": [
        {
          "license": {
            "id": "Artistic-2.0",
            "acknowledgement": "declared",
            "url": "https://spdx.org/licenses/Artistic-2.0.json"
          }
        }
      ],
      "copyright": "© 2006 - 2025 Yet Another Society",
      "externalReferences": [
        {
          "url": "https://github.com/rakudo/rakudo",
          "type": "distribution"
        },
        {
          "url": "https://github.com/rakudo/rakudo/issues",
          "type": "issue-tracker"
        },
        {
          "url": "https://github.com/rakudo/rakudo/archive/3aea31ed1.zip",
          "type": "source-distribution"
        },
        {
          "url": "irc://libera.chat/raku",
          "type": "chat"
        }
      ]
    },
    {
      "type": "platform",
      "bom-ref": "moar",
      "authors": [
        {
          "bom-ref": "TheMoarVMTeam",
          "name": "The MoarVM Team"
        }
      ],
      "publisher": "The MoarVM Team",
      "group": "The MoarVM Team",
      "name": "Moar",
      "version": "2025.06-5-gb1c74b8d8",
      "description": "Short for \"Metamodel On A Runtime\", MoarVM is a modern virtual machine built for the Rakudo compiler and the NQP Compiler Toolchain.",
      "scope": "required",
      "licenses": [
        {
          "license": {
            "id": "Artistic-2.0",
            "acknowledgement": "declared",
            "url": "https://spdx.org/licenses/Artistic-2.0.json"
          }
        }
      ],
      "copyright": "© 2012 - 2025 Jonathan Worthington",
      "externalReferences": [
        {
          "url": "https://github.com/MoarVM/MoarVM",
          "type": "distribution"
        },
        {
          "url": "https://github.com/MoarVM/MoarVM/issues",
          "type": "issue-tracker"
        },
        {
          "url": "irc://libera.chat/moarvm",
          "type": "chat"
        },
        {
          "url": "https://github.com/MoarVM/MoarVM.git/archive/refs/tags/b1c74b8d8.zip",
          "type": "source-distribution"
        }
      ]
    }
  ],
  "externalReferences": [
    {
      "url": "git://github.com/kimryan/raku-Lingua-EN-Fathom",
      "type": "distribution"
    },
    {
      "url": "https://raku.land/zef:kimryan/Lingua::EN::Fathom?v=0.0.1",
      "type": "documentation"
    },
    {
      "url": "https://spdx.org/licenses/Artistic-2.0.json",
      "type": "license"
    }
  ],
  "dependencies": [
    {
      "ref": "Rakudo",
      "dependsOn": [
        "moar"
      ]
    },
    {
      "ref": "pkg:raku/zef:lizmat/SBOM::Raku@0.0.10",
      "dependsOn": [
        "Rakudo"
      ]
    }
  ]
}