{"source-url":"git://github.com/alabamenhu/UserTimezone.git","auth":"github:alabamenhu","description":"A simple module for determining the user's timezone.","license":"Artistic-2.0","build-depends":[],"dist":"UserTimezone:ver<0.2>:auth<github:alabamenhu>","resources":["windows-zones.data","windows-regions.data"],"name":"UserTimezone","test-depends":[],"perl":"6.*","version":"0.2","authors":["Matthew ‘Matéu’ Stephen STUCKWISCH <mateu@softastur.com>"],"provides":{"Intl::UserTimezone":"lib/Intl/UserTimezone.pm6"},"depends":[]}