{"auth":"zef:lizmat","authors":["Elizabeth Mattijsen"],"build-depends":[],"depends":{"runtime":{"requires":["P5tie:ver<0.0.15+>:auth<zef:lizmat>"]}},"description":"Raku port of Perl's Tie::Hash module","dist":"Tie::Hash:ver<0.0.9>:auth<zef:lizmat>","license":"Artistic-2.0","name":"Tie::Hash","provides":{"Tie::Hash":"lib/Tie/Hash.rakumod"},"raku":"6.c","release-date":"2025-10-14","resources":[],"source-url":"https://raw.githubusercontent.com/raku/REA/main/archive/T/Tie%3A%3AHash/Tie%3A%3AHash%3Aver%3C0.0.9%3E%3Aauth%3Czef%3Alizmat%3E.tar.gz","support":{"bugtracker":"https://github.com/lizmat/Tie-Hash/issues","email":"liz@raku.rocks","source":"https://github.com/lizmat/Tie-Hash.git"},"tags":["UTILS","CPAN5"],"test-depends":[],"version":"0.0.9"}