{"support":{"source":"https://github.com/CurtTilmes/perl6-libuuid.git","bugtracker":"https://github.com/CurtTilmes/perl6-libuuid/issues"},"test-depends":["Test","Test::When","Test::META"],"version":"0.5","auth":"github:CurtTilmes","provides":{"LibUUID":"lib/LibUUID.pm6"},"source-url":"https://github.com/CurtTilmes/perl6-libuuid.git","description":"Perl 6 bindings for libuuid, for UUID generation","perl":"6.*","tags":["UUID"],"authors":["Curt Tilmes <ctilmes@cpan.org>"],"name":"LibUUID","dist":"LibUUID:ver<0.5>:auth<github:CurtTilmes>","depends":["NativeCall","NativeLibs:auth<github:salortiz>"],"license":"Artistic-2.0"}