{"provides":{"FastCGI::NativeCall::PSGI":"lib/FastCGI/NativeCall/PSGI.pm6"},"raku":"6.*","source-url":"http://www.cpan.org/authors/id/J/JS/JSTOWE/Perl6/FastCGI-NativeCall-PSGI-0.0.5.tar.gz","test-depends":[],"authors":["carbin","jonathanstowe"],"resources":[],"perl":"6.*","auth":"cpan:JSTOWE","dist":"FastCGI::NativeCall::PSGI:ver<0.0.5>:auth<cpan:JSTOWE>:api<1,0>","author":"github:carbin","build-depends":[],"description":"A PSGI interface for FastCGI::NativeCall","name":"FastCGI::NativeCall::PSGI","license":"ISC","meta-version":"1","version":"0.0.5","support":{"source":"https://github.com/jonathanstowe/raku-fcgi-psgi.git","bugtracker":"https://github.com/jonathanstowe/raku-fcgi-psgi/issues"},"tags":["http","fastcgi","fcgi","psgi"],"depends":["PSGI","FastCGI::NativeCall"],"api":"1,0"}