{"api":"1.0","authors":["Jonathan Stpwe <jns+gh@gellyfish.co.uk"],"depends":["LibraryCheck","NativeHelpers::Array"],"auth":"cpan:JSTOWE","description":"Binding for libsodium password hashing","license":"Artistic-2.0","raku":"6.*","test-depends":["LibraryCheck"],"meta-version":"1","name":"Crypt::SodiumScrypt","resources":[],"provides":{"Crypt::SodiumScrypt":"lib/Crypt/SodiumScrypt.pm"},"build-depends":[],"perl":"6.*","version":"0.0.3","source-url":"http://www.cpan.org/authors/id/J/JS/JSTOWE/Perl6/Crypt-SodiumScrypt-0.0.3.tar.gz","tags":["crypto","libsodium","password","scrypt"],"support":{"email":"jns+gh@gellyfish.co.uk","bugtracker":"https://github.com/jonathanstowe/Crypt-SodiumScrypt/issues","source":"https://github.com/jonathanstowe/Crypt-SodiumScrypt.git"},"dist":"Crypt::SodiumScrypt:ver<0.0.3>:auth<cpan:JSTOWE>:api<1.0>"}