{"auth":"cpan:WARRINGD","authors":["David Warring"],"build-depends":[],"depends":["CSS::Grammar:ver<0.3.9+>","JSON::Fast"],"description":"CSS3 Module Level 3 Selectors","dist":"CSS::Module::CSS3::Selectors:ver<0.0.5>:auth<cpan:WARRINGD>","license":"Artistic-2.0","name":"CSS::Module::CSS3::Selectors","perl":"6.*","provides":{"CSS::Module::CSS3::Selectors":"lib/CSS/Module/CSS3/Selectors.rakumod","CSS::Module::CSS3::Selectors::Actions":"lib/CSS/Module/CSS3/Selectors/Actions.rakumod"},"resources":[],"source-url":"https://raw.githubusercontent.com/raku/REA/main/archive/C/CSS::Module::CSS3::Selectors/CSS::Module::CSS3::Selectors:ver%3C0.0.5%3E:auth%3Ccpan:WARRINGD%3E.tar.gz","tags":[],"test-depends":[],"version":"0.0.5"}