{"auth":"zef:patrickb","authors":["Patrick Böker <patrick.boeker@posteo.de>"],"depends":[],"description":"Raku source code lexer","dist":"Rainbow:ver<0.4.1>:auth<zef:patrickb>","license":"Artistic-2.0","name":"Rainbow","perl":"6.d","provides":{"Rainbow":"lib/Rainbow.rakumod","Rainbow::RakuGrammar":"lib/Rainbow/RakuGrammar.rakumod","Rainbow::RakuGrammarActions":"lib/Rainbow/RakuGrammarActions.rakumod","Rainbow::Token":"lib/Rainbow/Token.rakumod"},"release-date":"2025-12-15","source-url":"https://raw.githubusercontent.com/raku/REA/main/archive/R/Rainbow/Rainbow%3Aver%3C0.4.1%3E%3Aauth%3Czef%3Apatrickb%3E.tar.gz","support":{"bugtracker":"https://todo.sr.ht/~patrickb/Rainbow","mailinglist":"https://lists.sr.ht/~patrickb/Rainbow-devel","source":"https://git.sr.ht/~patrickb/Rainbow"},"tags":["Raku","Lexer","Highlight"],"version":"0.4.1"}