{"author":"Adriaan Larmuseau","provides":{"Avro::Auxiliary":"lib/Avro/Auxiliary.pm","Avro::Encode":"lib/Avro/Encode.pm","Avro":"lib/Avro.pm","Avro::DataFile":"lib/Avro/DataFile.pm","Avro::Schema":"lib/Avro/Schema.pm","Avro::Decode":"lib/Avro/Decode.pm"},"dist":"Avro:ver<0.1.1>:auth<github:sylvarant>","name":"Avro","auth":"github:sylvarant","perl":"6.*","source-url":"git://github.com/sylvarant/Avro.git","description":"Perl6 Avro Data Serialization","depends":["JSON::Tiny","Compress::Zlib"],"version":"0.1.1"}