{"api":"1.0","auth":"cpan:JSTOWE","authors":["Jonathan Stowe <jns+gh@gellyfish.co.uk>"],"build-depends":[],"depends":["DBIish","NativeHelpers::CStruct"],"description":"Reactive interface to PostgreSQL notifies","dist":"Pg::Notify:ver<0.0.5>:auth<cpan:JSTOWE>:api<1.0>","license":"Artistic-2.0","meta-version":"1","name":"Pg::Notify","perl":"6.*","provides":{"Pg::Notify":"lib/Pg/Notify.pm"},"raku":"6.*","release-date":"2020-02-18","resources":[],"source-url":"https://raw.githubusercontent.com/raku/REA/main/archive/P/Pg%3A%3ANotify/Pg%3A%3ANotify%3Aver%3C0.0.5%3E%3Aauth%3Ccpan%3AJSTOWE%3E%3Aapi%3C1.0%3E.tar.gz","support":{"bugtracker":"https://github.com/jonathanstowe/Pg-Notify/issues","email":"jns+gh@gellyfish.co.uk","source":"https://github.com/jonathanstowe/Pg-Notify.git"},"tags":["database","postgres","notification"],"test-depends":["DBIish"],"version":"0.0.5"}