{
  "$schema": "http://cyclonedx.org/schema/bom-1.6.schema.json",
  "bomFormat": "CycloneDX",
  "specVersion": "1.6",
  "version": 1,
  "metadata": {
    "timestamp": "2025-08-08T19:59:30+00:00",
    "lifecycles": [
      {
        "phase": "pre-build"
      }
    ],
    "authors": [
      {
        "bom-ref": "LeonTimmermans",
        "name": "Leon Timmermans"
      }
    ],
    "component": {
      "type": "library",
      "mime-type": "text/plain",
      "bom-ref": "pkg:raku/cpan:LEONT/Getopt::Subcommands@0.1.0",
      "authors": [
        {
          "bom-ref": "LeonTimmermans",
          "name": "Leon Timmermans"
        }
      ],
      "publisher": "cpan",
      "group": "cpan:LEONT",
      "name": "Getopt::Subcommands",
      "version": "0.1.0",
      "description": "A Getopt::Long extension for subcommands",
      "scope": "required",
      "hashes": [
        {
          "alg": "MD5",
          "content": "20608c4c02fe8fc4abfef95ce37d91d7"
        },
        {
          "alg": "SHA-1",
          "content": "be951b08e0fb1127f2e5fed844218eb686fd035b"
        },
        {
          "alg": "SHA-256",
          "content": "3839c81b427db766844d022c3ae205c02bdc6b281398aa7ce1f5603ee11cdc8f"
        },
        {
          "alg": "SHA-384",
          "content": "fada8e0a6e0950da532e4014802ae1a85f7e7e334af22157cf56ba99f04e679b6719de8262d5d8f7bcdc764c840fc354"
        },
        {
          "alg": "SHA-512",
          "content": "4d46540534ac2b41d39295b72e951233136ec324695024258066b6494fb667af11782179fbe9fc6e9ef0ee0dc0479d503afa81b886f90ff001ccf204a4c56a77"
        }
      ],
      "licenses": [
        {
          "license": {
            "id": "Artistic-2.0",
            "acknowledgement": "declared",
            "url": "https://spdx.org/licenses/Artistic-2.0.json"
          }
        }
      ],
      "purl": "pkg:raku/cpan:LEONT/Getopt::Subcommands@0.1.0",
      "externalReferences": [
        {
          "url": "https://github.com/Leont/getopt-subcommands",
          "type": "distribution"
        },
        {
          "url": "https://raku.land/cpan:LEONT/Getopt::Subcommands?v=0.1.0",
          "type": "documentation"
        },
        {
          "url": "https://github.com/Leont/getopt-subcommands/issues",
          "type": "issue-tracker"
        },
        {
          "url": "https://spdx.org/licenses/Artistic-2.0.json",
          "type": "license"
        },
        {
          "url": "https://github.com/Leont/getopt-subcommands/archive/refs/tags/0.1.0.zip",
          "type": "source-distribution"
        }
      ]
    },
    "licenses": [
      {
        "license": {
          "id": "Artistic-2.0",
          "acknowledgement": "declared",
          "url": "https://spdx.org/licenses/Artistic-2.0.json"
        }
      }
    ],
    "tools": {
      "components": [
        {
          "type": "library",
          "mime-type": "text/plain",
          "bom-ref": "pkg:raku/zef:lizmat/SBOM::Raku@0.0.10",
          "authors": [
            {
              "bom-ref": "ElizabethMattijsen",
              "name": "Elizabeth Mattijsen"
            }
          ],
          "publisher": "zef",
          "group": "zef:lizmat",
          "name": "SBOM::Raku",
          "version": "0.0.10",
          "description": "Raku specific SBOM functionality",
          "scope": "required",
          "licenses": [
            {
              "license": {
                "id": "Artistic-2.0",
                "acknowledgement": "declared",
                "url": "https://spdx.org/licenses/Artistic-2.0.json"
              }
            }
          ],
          "purl": "pkg:raku/zef:lizmat/SBOM::Raku@0.0.10",
          "externalReferences": [
            {
              "url": "https://github.com/lizmat/SBOM-Raku",
              "type": "distribution"
            },
            {
              "url": "https://raku.land/zef:lizmat/SBOM::Raku?v=0.0.10",
              "type": "documentation"
            },
            {
              "url": "https://github.com/lizmat/SBOM-Raku/issues",
              "type": "issue-tracker"
            },
            {
              "url": "https://spdx.org/licenses/Artistic-2.0.json",
              "type": "license"
            },
            {
              "url": "https://github.com/lizmat/SBOM-Raku/archive/refs/tags/0.0.10.zip",
              "type": "source-distribution"
            },
            {
              "url": "mailto:liz@raku.rocks",
              "type": "support"
            }
          ],
          "tags": [
            "SBOM",
            "RAKU",
            "META"
          ]
        }
      ]
    }
  },
  "components": [
    {
      "type": "platform",
      "bom-ref": "Rakudo",
      "authors": [
        {
          "bom-ref": "RakudoCoreDevelopers",
          "name": "Rakudo Core Developers"
        }
      ],
      "publisher": "Rakudo Core Developers",
      "group": "Rakudo Core Developers",
      "name": "Rakudo",
      "version": "2025.06.1-12-g3aea31ed1",
      "description": "The Rakudo™ Compiler implementing the Raku® Programming Language",
      "scope": "required",
      "licenses": [
        {
          "license": {
            "id": "Artistic-2.0",
            "acknowledgement": "declared",
            "url": "https://spdx.org/licenses/Artistic-2.0.json"
          }
        }
      ],
      "copyright": "© 2006 - 2025 Yet Another Society",
      "externalReferences": [
        {
          "url": "https://github.com/rakudo/rakudo",
          "type": "distribution"
        },
        {
          "url": "https://github.com/rakudo/rakudo/issues",
          "type": "issue-tracker"
        },
        {
          "url": "https://github.com/rakudo/rakudo/archive/3aea31ed1.zip",
          "type": "source-distribution"
        },
        {
          "url": "irc://libera.chat/raku",
          "type": "chat"
        }
      ]
    },
    {
      "type": "platform",
      "bom-ref": "moar",
      "authors": [
        {
          "bom-ref": "TheMoarVMTeam",
          "name": "The MoarVM Team"
        }
      ],
      "publisher": "The MoarVM Team",
      "group": "The MoarVM Team",
      "name": "Moar",
      "version": "2025.06-5-gb1c74b8d8",
      "description": "Short for \"Metamodel On A Runtime\", MoarVM is a modern virtual machine built for the Rakudo compiler and the NQP Compiler Toolchain.",
      "scope": "required",
      "licenses": [
        {
          "license": {
            "id": "Artistic-2.0",
            "acknowledgement": "declared",
            "url": "https://spdx.org/licenses/Artistic-2.0.json"
          }
        }
      ],
      "copyright": "© 2012 - 2025 Jonathan Worthington",
      "externalReferences": [
        {
          "url": "https://github.com/MoarVM/MoarVM",
          "type": "distribution"
        },
        {
          "url": "https://github.com/MoarVM/MoarVM/issues",
          "type": "issue-tracker"
        },
        {
          "url": "irc://libera.chat/moarvm",
          "type": "chat"
        },
        {
          "url": "https://github.com/MoarVM/MoarVM.git/archive/refs/tags/b1c74b8d8.zip",
          "type": "source-distribution"
        }
      ]
    }
  ],
  "externalReferences": [
    {
      "url": "https://github.com/Leont/getopt-subcommands",
      "type": "distribution"
    },
    {
      "url": "https://raku.land/cpan:LEONT/Getopt::Subcommands?v=0.1.0",
      "type": "documentation"
    },
    {
      "url": "https://github.com/Leont/getopt-subcommands/issues",
      "type": "issue-tracker"
    },
    {
      "url": "https://spdx.org/licenses/Artistic-2.0.json",
      "type": "license"
    },
    {
      "url": "https://github.com/Leont/getopt-subcommands/archive/refs/tags/0.1.0.zip",
      "type": "source-distribution"
    }
  ],
  "dependencies": [
    {
      "ref": "Rakudo",
      "dependsOn": [
        "moar"
      ]
    },
    {
      "ref": "pkg:raku/zef:lizmat/SBOM::Raku@0.0.10",
      "dependsOn": [
        "Rakudo"
      ]
    }
  ]
}