{
  "$schema": "http://cyclonedx.org/schema/bom-1.6.schema.json",
  "bomFormat": "CycloneDX",
  "specVersion": "1.6",
  "version": 1,
  "metadata": {
    "timestamp": "2025-08-08T20:49:05+00:00",
    "lifecycles": [
      {
        "phase": "pre-build"
      }
    ],
    "authors": [
      {
        "bom-ref": "GeoffreyBroadwell",
        "name": "Geoffrey Broadwell"
      }
    ],
    "component": {
      "type": "library",
      "mime-type": "text/plain",
      "bom-ref": "pkg:raku/zef:japhb/MUGS::Games@0.1.4",
      "authors": [
        {
          "bom-ref": "GeoffreyBroadwell",
          "name": "Geoffrey Broadwell"
        }
      ],
      "publisher": "zef",
      "group": "zef:japhb",
      "name": "MUGS::Games",
      "version": "0.1.4",
      "description": "Free-as-in-speech game implementations for MUGS (Multi-User Gaming Services)",
      "scope": "required",
      "hashes": [
        {
          "alg": "MD5",
          "content": "42fa443894bbcb9b04bcff96ba5ccc3b"
        },
        {
          "alg": "SHA-1",
          "content": "3649946c5fd8d39e2f6b0bea007965833202a40a"
        },
        {
          "alg": "SHA-256",
          "content": "599dc18643f9409127ff034be5532691e587b9f1f3711c9441c0b660cb98f42b"
        },
        {
          "alg": "SHA-384",
          "content": "d9d3b4812aa0cb47381caba056fac01f9686ae20c1a3004a4d761d607a00c7a25786518495c1d83d268682ba3283f8c1"
        },
        {
          "alg": "SHA-512",
          "content": "5134c0d79d12f478e6b939611e6b75906f6966e39d4749d67783cc78fba952fec5b4c506ce95baed6b4797663e9f7134686d28c1c38966cedfd3239118b5a398"
        }
      ],
      "licenses": [
        {
          "license": {
            "id": "Artistic-2.0",
            "acknowledgement": "declared",
            "url": "https://spdx.org/licenses/Artistic-2.0.json"
          }
        }
      ],
      "purl": "pkg:raku/zef:japhb/MUGS::Games@0.1.4",
      "externalReferences": [
        {
          "url": "https://github.com/Raku-MUGS/MUGS-Games",
          "type": "distribution"
        },
        {
          "url": "https://raku.land/zef:japhb/MUGS::Games?v=0.1.4",
          "type": "documentation"
        },
        {
          "url": "https://github.com/Raku-MUGS/MUGS-Games/issues",
          "type": "issue-tracker"
        },
        {
          "url": "https://spdx.org/licenses/Artistic-2.0.json",
          "type": "license"
        },
        {
          "url": "https://github.com/Raku-MUGS/MUGS-Games/archive/refs/tags/0.1.4.zip",
          "type": "source-distribution"
        }
      ]
    },
    "licenses": [
      {
        "license": {
          "id": "Artistic-2.0",
          "acknowledgement": "declared",
          "url": "https://spdx.org/licenses/Artistic-2.0.json"
        }
      }
    ],
    "tools": {
      "components": [
        {
          "type": "library",
          "mime-type": "text/plain",
          "bom-ref": "pkg:raku/zef:lizmat/SBOM::Raku@0.0.10",
          "authors": [
            {
              "bom-ref": "ElizabethMattijsen",
              "name": "Elizabeth Mattijsen"
            }
          ],
          "publisher": "zef",
          "group": "zef:lizmat",
          "name": "SBOM::Raku",
          "version": "0.0.10",
          "description": "Raku specific SBOM functionality",
          "scope": "required",
          "licenses": [
            {
              "license": {
                "id": "Artistic-2.0",
                "acknowledgement": "declared",
                "url": "https://spdx.org/licenses/Artistic-2.0.json"
              }
            }
          ],
          "purl": "pkg:raku/zef:lizmat/SBOM::Raku@0.0.10",
          "externalReferences": [
            {
              "url": "https://github.com/lizmat/SBOM-Raku",
              "type": "distribution"
            },
            {
              "url": "https://raku.land/zef:lizmat/SBOM::Raku?v=0.0.10",
              "type": "documentation"
            },
            {
              "url": "https://github.com/lizmat/SBOM-Raku/issues",
              "type": "issue-tracker"
            },
            {
              "url": "https://spdx.org/licenses/Artistic-2.0.json",
              "type": "license"
            },
            {
              "url": "https://github.com/lizmat/SBOM-Raku/archive/refs/tags/0.0.10.zip",
              "type": "source-distribution"
            },
            {
              "url": "mailto:liz@raku.rocks",
              "type": "support"
            }
          ],
          "tags": [
            "SBOM",
            "RAKU",
            "META"
          ]
        }
      ]
    }
  },
  "components": [
    {
      "type": "platform",
      "bom-ref": "Rakudo",
      "authors": [
        {
          "bom-ref": "RakudoCoreDevelopers",
          "name": "Rakudo Core Developers"
        }
      ],
      "publisher": "Rakudo Core Developers",
      "group": "Rakudo Core Developers",
      "name": "Rakudo",
      "version": "2025.06.1-12-g3aea31ed1",
      "description": "The Rakudo™ Compiler implementing the Raku® Programming Language",
      "scope": "required",
      "licenses": [
        {
          "license": {
            "id": "Artistic-2.0",
            "acknowledgement": "declared",
            "url": "https://spdx.org/licenses/Artistic-2.0.json"
          }
        }
      ],
      "copyright": "© 2006 - 2025 Yet Another Society",
      "externalReferences": [
        {
          "url": "https://github.com/rakudo/rakudo",
          "type": "distribution"
        },
        {
          "url": "https://github.com/rakudo/rakudo/issues",
          "type": "issue-tracker"
        },
        {
          "url": "https://github.com/rakudo/rakudo/archive/3aea31ed1.zip",
          "type": "source-distribution"
        },
        {
          "url": "irc://libera.chat/raku",
          "type": "chat"
        }
      ]
    },
    {
      "type": "platform",
      "bom-ref": "moar",
      "authors": [
        {
          "bom-ref": "TheMoarVMTeam",
          "name": "The MoarVM Team"
        }
      ],
      "publisher": "The MoarVM Team",
      "group": "The MoarVM Team",
      "name": "Moar",
      "version": "2025.06-5-gb1c74b8d8",
      "description": "Short for \"Metamodel On A Runtime\", MoarVM is a modern virtual machine built for the Rakudo compiler and the NQP Compiler Toolchain.",
      "scope": "required",
      "licenses": [
        {
          "license": {
            "id": "Artistic-2.0",
            "acknowledgement": "declared",
            "url": "https://spdx.org/licenses/Artistic-2.0.json"
          }
        }
      ],
      "copyright": "© 2012 - 2025 Jonathan Worthington",
      "externalReferences": [
        {
          "url": "https://github.com/MoarVM/MoarVM",
          "type": "distribution"
        },
        {
          "url": "https://github.com/MoarVM/MoarVM/issues",
          "type": "issue-tracker"
        },
        {
          "url": "irc://libera.chat/moarvm",
          "type": "chat"
        },
        {
          "url": "https://github.com/MoarVM/MoarVM.git/archive/refs/tags/b1c74b8d8.zip",
          "type": "source-distribution"
        }
      ]
    }
  ],
  "externalReferences": [
    {
      "url": "https://github.com/Raku-MUGS/MUGS-Games",
      "type": "distribution"
    },
    {
      "url": "https://raku.land/zef:japhb/MUGS::Games?v=0.1.4",
      "type": "documentation"
    },
    {
      "url": "https://github.com/Raku-MUGS/MUGS-Games/issues",
      "type": "issue-tracker"
    },
    {
      "url": "https://spdx.org/licenses/Artistic-2.0.json",
      "type": "license"
    },
    {
      "url": "https://github.com/Raku-MUGS/MUGS-Games/archive/refs/tags/0.1.4.zip",
      "type": "source-distribution"
    }
  ],
  "dependencies": [
    {
      "ref": "Rakudo",
      "dependsOn": [
        "moar"
      ]
    },
    {
      "ref": "pkg:raku/zef:lizmat/SBOM::Raku@0.0.10",
      "dependsOn": [
        "Rakudo"
      ]
    }
  ]
}