{"authors":["Geoffrey Broadwell"],"description":"Common base components for RPGs","build-depends":[],"depends":[],"perl":"6.c","dist":"RPG::Base:ver<0.0.9>:auth<github:japhb>","test-depends":[],"name":"RPG::Base","version":"0.0.9","resources":[],"tags":["RPG","Base","Adventure","Creature"],"provides":{"RPG::Base::ThingContainer":"lib/RPG/Base/ThingContainer.pm6","RPG::Base::Location":"lib/RPG/Base/Location.pm6","RPG::Base::Container":"lib/RPG/Base/Container.pm6","RPG::Base::Creature":"lib/RPG/Base/Creature.pm6","RPG::Base::AreaMap":"lib/RPG/Base/AreaMap.pm6","RPG::Base::StatModifier":"lib/RPG/Base/StatModifier.pm6","RPG::Base::Adventure":"lib/RPG/Base/Adventure.pm6","RPG::Base::Thing":"lib/RPG/Base/Thing.pm6","RPG::Base::Grouping":"lib/RPG/Base/Grouping.pm6","RPG::Base::SlottedContainer":"lib/RPG/Base/SlottedContainer.pm6","RPG::Base::Party":"lib/RPG/Base/Party.pm6","RPG::Base::Named":"lib/RPG/Base/Named.pm6","RPG::Base::StatsBearer":"lib/RPG/Base/StatsBearer.pm6","RPG::Base":"lib/RPG/Base.pm6"},"license":"Artistic-2.0","source-url":"git://github.com/japhb/RPG-Base.git"}