{
  "$schema": "http://cyclonedx.org/schema/bom-1.6.schema.json",
  "bomFormat": "CycloneDX",
  "specVersion": "1.6",
  "version": 1,
  "metadata": {
    "timestamp": "2025-08-08T19:58:52+00:00",
    "lifecycles": [
      {
        "phase": "pre-build"
      }
    ],
    "authors": [
      {
        "bom-ref": "BrianDuggan",
        "name": "Brian Duggan"
      }
    ],
    "component": {
      "type": "library",
      "mime-type": "text/plain",
      "bom-ref": "pkg:raku/zef:bduggan/Geo::Polyline@0.0.2",
      "authors": [
        {
          "bom-ref": "BrianDuggan",
          "name": "Brian Duggan"
        }
      ],
      "publisher": "zef",
      "group": "zef:bduggan",
      "name": "Geo::Polyline",
      "version": "0.0.2",
      "description": "Encode and decode Google polyline strings",
      "scope": "required",
      "hashes": [
        {
          "alg": "MD5",
          "content": "af77f6135120d796c8a325002e907ad5"
        },
        {
          "alg": "SHA-1",
          "content": "a081c2a6e2e938159c81ee9c016db7d3fcbe6b61"
        },
        {
          "alg": "SHA-256",
          "content": "b6a36ba1b77b1f0d41889b36fee8a2493c5f437ad86add112e7f2c6cde11c73a"
        },
        {
          "alg": "SHA-384",
          "content": "4da9c184c51833febd8a8cada5d17de593bf6341eaafaa26d7f8abf004dd239ed69cfab575d686c937493e788058194c"
        },
        {
          "alg": "SHA-512",
          "content": "36dea86d40bc25b7d63f440efd669e4e6f112764b8fee2c8991b92238ed2fe3629b1bc32d01492e0b840334379fd54291063cbbf9053e8dcbaa18aee67b7732c"
        }
      ],
      "licenses": [
        {
          "license": {
            "id": "MIT",
            "acknowledgement": "declared",
            "url": "https://spdx.org/licenses/MIT.json"
          }
        }
      ],
      "purl": "pkg:raku/zef:bduggan/Geo::Polyline@0.0.2",
      "externalReferences": [
        {
          "url": "git://github.com/bduggan/raku-geo-polyline",
          "type": "distribution"
        },
        {
          "url": "https://raku.land/zef:bduggan/Geo::Polyline?v=0.0.2",
          "type": "documentation"
        },
        {
          "url": "https://spdx.org/licenses/MIT.json",
          "type": "license"
        }
      ],
      "tags": [
        "geo"
      ]
    },
    "licenses": [
      {
        "license": {
          "id": "MIT",
          "acknowledgement": "declared",
          "url": "https://spdx.org/licenses/MIT.json"
        }
      }
    ],
    "tools": {
      "components": [
        {
          "type": "library",
          "mime-type": "text/plain",
          "bom-ref": "pkg:raku/zef:lizmat/SBOM::Raku@0.0.10",
          "authors": [
            {
              "bom-ref": "ElizabethMattijsen",
              "name": "Elizabeth Mattijsen"
            }
          ],
          "publisher": "zef",
          "group": "zef:lizmat",
          "name": "SBOM::Raku",
          "version": "0.0.10",
          "description": "Raku specific SBOM functionality",
          "scope": "required",
          "licenses": [
            {
              "license": {
                "id": "Artistic-2.0",
                "acknowledgement": "declared",
                "url": "https://spdx.org/licenses/Artistic-2.0.json"
              }
            }
          ],
          "purl": "pkg:raku/zef:lizmat/SBOM::Raku@0.0.10",
          "externalReferences": [
            {
              "url": "https://github.com/lizmat/SBOM-Raku",
              "type": "distribution"
            },
            {
              "url": "https://raku.land/zef:lizmat/SBOM::Raku?v=0.0.10",
              "type": "documentation"
            },
            {
              "url": "https://github.com/lizmat/SBOM-Raku/issues",
              "type": "issue-tracker"
            },
            {
              "url": "https://spdx.org/licenses/Artistic-2.0.json",
              "type": "license"
            },
            {
              "url": "https://github.com/lizmat/SBOM-Raku/archive/refs/tags/0.0.10.zip",
              "type": "source-distribution"
            },
            {
              "url": "mailto:liz@raku.rocks",
              "type": "support"
            }
          ],
          "tags": [
            "SBOM",
            "RAKU",
            "META"
          ]
        }
      ]
    }
  },
  "components": [
    {
      "type": "platform",
      "bom-ref": "Rakudo",
      "authors": [
        {
          "bom-ref": "RakudoCoreDevelopers",
          "name": "Rakudo Core Developers"
        }
      ],
      "publisher": "Rakudo Core Developers",
      "group": "Rakudo Core Developers",
      "name": "Rakudo",
      "version": "2025.06.1-12-g3aea31ed1",
      "description": "The Rakudo™ Compiler implementing the Raku® Programming Language",
      "scope": "required",
      "licenses": [
        {
          "license": {
            "id": "Artistic-2.0",
            "acknowledgement": "declared",
            "url": "https://spdx.org/licenses/Artistic-2.0.json"
          }
        }
      ],
      "copyright": "© 2006 - 2025 Yet Another Society",
      "externalReferences": [
        {
          "url": "https://github.com/rakudo/rakudo",
          "type": "distribution"
        },
        {
          "url": "https://github.com/rakudo/rakudo/issues",
          "type": "issue-tracker"
        },
        {
          "url": "https://github.com/rakudo/rakudo/archive/3aea31ed1.zip",
          "type": "source-distribution"
        },
        {
          "url": "irc://libera.chat/raku",
          "type": "chat"
        }
      ]
    },
    {
      "type": "platform",
      "bom-ref": "moar",
      "authors": [
        {
          "bom-ref": "TheMoarVMTeam",
          "name": "The MoarVM Team"
        }
      ],
      "publisher": "The MoarVM Team",
      "group": "The MoarVM Team",
      "name": "Moar",
      "version": "2025.06-5-gb1c74b8d8",
      "description": "Short for \"Metamodel On A Runtime\", MoarVM is a modern virtual machine built for the Rakudo compiler and the NQP Compiler Toolchain.",
      "scope": "required",
      "licenses": [
        {
          "license": {
            "id": "Artistic-2.0",
            "acknowledgement": "declared",
            "url": "https://spdx.org/licenses/Artistic-2.0.json"
          }
        }
      ],
      "copyright": "© 2012 - 2025 Jonathan Worthington",
      "externalReferences": [
        {
          "url": "https://github.com/MoarVM/MoarVM",
          "type": "distribution"
        },
        {
          "url": "https://github.com/MoarVM/MoarVM/issues",
          "type": "issue-tracker"
        },
        {
          "url": "irc://libera.chat/moarvm",
          "type": "chat"
        },
        {
          "url": "https://github.com/MoarVM/MoarVM.git/archive/refs/tags/b1c74b8d8.zip",
          "type": "source-distribution"
        }
      ]
    }
  ],
  "externalReferences": [
    {
      "url": "git://github.com/bduggan/raku-geo-polyline",
      "type": "distribution"
    },
    {
      "url": "https://raku.land/zef:bduggan/Geo::Polyline?v=0.0.2",
      "type": "documentation"
    },
    {
      "url": "https://spdx.org/licenses/MIT.json",
      "type": "license"
    }
  ],
  "dependencies": [
    {
      "ref": "Rakudo",
      "dependsOn": [
        "moar"
      ]
    },
    {
      "ref": "pkg:raku/zef:lizmat/SBOM::Raku@0.0.10",
      "dependsOn": [
        "Rakudo"
      ]
    }
  ]
}