{"auth":"cpan:VRURG","authors":["Vadim Belman <vrurg@cpan.org>"],"build-depends":["META6","p6doc","Pod::To::Markdown"],"depends":[],"description":"IPv4/IPv6 manipulation","dist":"IP::Addr:ver<0.0.3>:auth<cpan:VRURG>","license":"Artistic-2.0","meta-version":"0","name":"IP::Addr","perl":"6.*","production":true,"provides":{"IP::Addr":"lib/IP/Addr.pm6","IP::Addr::Common":"lib/IP/Addr/Common.pm6","IP::Addr::Handler":"lib/IP/Addr/Handler.pm6","IP::Addr::v4":"lib/IP/Addr/v4.pm6","IP::Addr::v6":"lib/IP/Addr/v6.pm6"},"release-date":"2020-01-28","resources":[],"source-url":"https://raw.githubusercontent.com/raku/REA/main/archive/I/IP::Addr/IP::Addr:ver%3C0.0.3%3E:auth%3Ccpan:VRURG%3E.tar.gz","support":{"source":"https://github.com/vrurg/raku-IP-Addr.git"},"tags":["IP","IPv4","IPv6"],"test-depends":["Test","Test::META","Test::When"],"version":"0.0.3"}