{"auth":"github:nicqrocks","authors":["Nic Quoziente"],"build-depends":[],"depends":["Net::HTTP::POST","JSON::Fast"],"description":"Easy way to send a message to Slack","dist":"WebService::Slack::Webhook:ver<0.1.1>:auth<github:nicqrocks>","emulates":{},"excludes":{},"license":"Artistic-2.0","name":"WebService::Slack::Webhook","perl":"6.c","provides":{"WebService::Slack::Webhook":"lib/WebService/Slack/Webhook.pm6"},"release-date":"2017-05-08","resources":[],"source-url":"https://raw.githubusercontent.com/raku/REA/main/archive/W/WebService%3A%3ASlack%3A%3AWebhook/WebService%3A%3ASlack%3A%3AWebhook%3Aver%3C0.1.1%3E%3Aauth%3Cgithub%3Anicqrocks%3E.tar.gz","superseded-by":{},"supersedes":{},"support":{"source":null},"tags":["web","slack"],"test-depends":[],"version":"0.1.1"}