{"auth":"github:raku-community-modules","authors":["Timothy Totten"],"depends":[],"description":"Add common math operations to DateTime objects.","dist":"DateTime::Math:ver<0.6.0>:auth<github:raku-community-modules>","license":"Artistic-2.0","meta-version":1,"name":"DateTime::Math","perl":"6.c","provides":{"DateTime::Math":"lib/DateTime/Math.pm6"},"release-date":"2021-01-28","source-url":"https://raw.githubusercontent.com/raku/REA/main/archive/D/DateTime%3A%3AMath/DateTime%3A%3AMath%3Aver%3C0.6.0%3E%3Aauth%3Cgithub%3Araku-community-modules%3E.tar.gz","version":"0.6.0"}