{"build-depends":[],"api":"","perl":"6.d","name":"IRC::Log","description":"role providing interface to IRC logs","path":"I/RC/IRC_LOG/7225b9653b9e5f6a57ae48c1943527c7fc9a0db2.tar.gz","resources":[],"test-depends":[],"license":"Artistic-2.0","tags":[],"dist":"IRC::Log:ver<0.0.20>:auth<zef:lizmat>","authors":["Elizabeth Mattijsen"],"depends":["Array::Sorted::Util:ver<0.0.8>:auth<zef:lizmat>","has-word:ver<0.0.1>:auth<zef:lizmat>"],"auth":"zef:lizmat","provides":{"IRC::Log":"lib/IRC/Log.rakumod"},"source-url":"https://github.com/lizmat/IRC-Log.git","version":"0.0.20"}