{"auth":"github:scovit","authors":["Vittore F. Scolari <vittore.scolari@pasteur.fr>"],"build-depends":[],"depends":[],"description":"A type for storing a caller allocated Buffer","dist":"NativeHelpers::CBuffer:ver<0.0.1>:auth<github:scovit>","license":"Artistic-2.0","name":"NativeHelpers::CBuffer","perl":"6.c","provides":{"NativeHelpers::CBuffer":"lib/NativeHelpers/CBuffer.pm6"},"release-date":"2017-09-12","repo-type":"git","resources":[],"source-url":"https://raw.githubusercontent.com/raku/REA/main/archive/N/NativeHelpers%3A%3ACBuffer/NativeHelpers%3A%3ACBuffer%3Aver%3C0.0.1%3E%3Aauth%3Cgithub%3Ascovit%3E.tar.gz","tags":["NativeCall","Utilities","Blob","Pointer","CPointer"],"test-depends":[],"version":"0.0.1"}