{
  "$schema": "http://cyclonedx.org/schema/bom-1.6.schema.json",
  "bomFormat": "CycloneDX",
  "specVersion": "1.6",
  "version": 1,
  "metadata": {
    "timestamp": "2026-02-03T00:06:19+00:00",
    "lifecycles": [
      {
        "phase": "pre-build"
      }
    ],
    "authors": [
      {
        "bom-ref": "ElizabethMattijsen",
        "name": "Elizabeth Mattijsen"
      },
      {
        "bom-ref": "ZoffixZnet",
        "name": "Zoffix Znet"
      }
    ],
    "component": {
      "type": "library",
      "mime-type": "text/plain",
      "bom-ref": "pkg:raku/zef:lizmat/IRC::Client@4.0.15",
      "authors": [
        {
          "bom-ref": "ElizabethMattijsen",
          "name": "Elizabeth Mattijsen"
        },
        {
          "bom-ref": "ZoffixZnet",
          "name": "Zoffix Znet"
        }
      ],
      "publisher": "zef",
      "group": "zef:lizmat",
      "name": "IRC::Client",
      "version": "4.0.15",
      "description": "Extendable Internet Relay Chat client",
      "scope": "required",
      "hashes": [
        {
          "alg": "MD5",
          "content": "731e59ccea1f5e29e724cf1f5ce49689"
        },
        {
          "alg": "SHA-1",
          "content": "7ae7d05f6f4ed4b654f2281a1d052354dd3d7895"
        },
        {
          "alg": "SHA-256",
          "content": "85a29027bf918bc32c66cf351fad177bf45be2b86207ffe97d19c31eb8b834e2"
        },
        {
          "alg": "SHA-384",
          "content": "cbb58ab043f1bcd90462fe198201120d9b747a6414b1e5a175892fe2c08ea4937f652a64cfabfdfd78535399b643451f"
        },
        {
          "alg": "SHA-512",
          "content": "7552b844006f3c062d82fbcca560ec50d723c38a5f299158851e500eca96d7c23d1db2588f4d60c24c8c24ba449b9b14582296a6a1f2d8e84956a0678a15a808"
        }
      ],
      "licenses": [
        {
          "license": {
            "id": "Artistic-2.0",
            "acknowledgement": "declared",
            "url": "https://spdx.org/licenses/Artistic-2.0.json"
          }
        }
      ],
      "purl": "pkg:raku/zef:lizmat/IRC::Client@4.0.15",
      "externalReferences": [
        {
          "url": "https://github.com/lizmat/IRC-Client",
          "type": "distribution"
        },
        {
          "url": "https://raku.land/zef:lizmat/IRC::Client?v=4.0.15",
          "type": "documentation"
        },
        {
          "url": "https://github.com/lizmat/IRC-Client/issues",
          "type": "issue-tracker"
        },
        {
          "url": "https://spdx.org/licenses/Artistic-2.0.json",
          "type": "license"
        },
        {
          "url": "https://github.com/lizmat/IRC-Client/archive/refs/tags/4.0.15.zip",
          "type": "source-distribution"
        },
        {
          "url": "mailto:liz@raku.rocks",
          "type": "support"
        }
      ],
      "tags": [
        "NET",
        "IRC",
        "CLIENT"
      ]
    },
    "licenses": [
      {
        "license": {
          "id": "Artistic-2.0",
          "acknowledgement": "declared",
          "url": "https://spdx.org/licenses/Artistic-2.0.json"
        }
      }
    ],
    "tools": {
      "components": [
        {
          "type": "library",
          "mime-type": "text/plain",
          "bom-ref": "pkg:raku/zef:lizmat/SBOM::Raku@0.0.12",
          "authors": [
            {
              "bom-ref": "ElizabethMattijsen",
              "name": "Elizabeth Mattijsen"
            }
          ],
          "publisher": "zef",
          "group": "zef:lizmat",
          "name": "SBOM::Raku",
          "version": "0.0.12",
          "description": "Raku specific SBOM functionality",
          "scope": "required",
          "licenses": [
            {
              "license": {
                "id": "Artistic-2.0",
                "acknowledgement": "declared",
                "url": "https://spdx.org/licenses/Artistic-2.0.json"
              }
            }
          ],
          "purl": "pkg:raku/zef:lizmat/SBOM::Raku@0.0.12",
          "externalReferences": [
            {
              "url": "https://github.com/lizmat/SBOM-Raku",
              "type": "distribution"
            },
            {
              "url": "https://raku.land/zef:lizmat/SBOM::Raku?v=0.0.12",
              "type": "documentation"
            },
            {
              "url": "https://github.com/lizmat/SBOM-Raku/issues",
              "type": "issue-tracker"
            },
            {
              "url": "https://spdx.org/licenses/Artistic-2.0.json",
              "type": "license"
            },
            {
              "url": "https://github.com/lizmat/SBOM-Raku/archive/refs/tags/0.0.12.zip",
              "type": "source-distribution"
            },
            {
              "url": "mailto:liz@raku.rocks",
              "type": "support"
            }
          ],
          "tags": [
            "SBOM",
            "RAKU",
            "META"
          ]
        }
      ]
    }
  },
  "components": [
    {
      "type": "platform",
      "bom-ref": "Rakudo",
      "authors": [
        {
          "bom-ref": "RakudoCoreDevelopers",
          "name": "Rakudo Core Developers"
        }
      ],
      "publisher": "Rakudo Core Developers",
      "group": "Rakudo Core Developers",
      "name": "Rakudo",
      "version": "2026.01",
      "description": "The Rakudo™ Compiler implementing the Raku® Programming Language",
      "scope": "required",
      "licenses": [
        {
          "license": {
            "id": "Artistic-2.0",
            "acknowledgement": "declared",
            "url": "https://spdx.org/licenses/Artistic-2.0.json"
          }
        }
      ],
      "copyright": "© 2006 - 2026 Yet Another Society",
      "externalReferences": [
        {
          "url": "https://github.com/rakudo/rakudo",
          "type": "distribution"
        },
        {
          "url": "https://github.com/rakudo/rakudo/issues",
          "type": "issue-tracker"
        },
        {
          "url": "https://github.com/rakudo/rakudo/archive/2026.01.zip",
          "type": "source-distribution"
        },
        {
          "url": "irc://libera.chat/raku",
          "type": "chat"
        }
      ]
    },
    {
      "type": "platform",
      "bom-ref": "moar",
      "authors": [
        {
          "bom-ref": "TheMoarVMTeam",
          "name": "The MoarVM Team"
        }
      ],
      "publisher": "The MoarVM Team",
      "group": "The MoarVM Team",
      "name": "Moar",
      "version": "2026.01",
      "description": "Short for \"Metamodel On A Runtime\", MoarVM is a modern virtual machine built for the Rakudo compiler and the NQP Compiler Toolchain.",
      "scope": "required",
      "licenses": [
        {
          "license": {
            "id": "Artistic-2.0",
            "acknowledgement": "declared",
            "url": "https://spdx.org/licenses/Artistic-2.0.json"
          }
        }
      ],
      "copyright": "© 2012 - 2026 Jonathan Worthington",
      "externalReferences": [
        {
          "url": "https://github.com/MoarVM/MoarVM",
          "type": "distribution"
        },
        {
          "url": "https://github.com/MoarVM/MoarVM/issues",
          "type": "issue-tracker"
        },
        {
          "url": "irc://libera.chat/moarvm",
          "type": "chat"
        },
        {
          "url": "https://github.com/MoarVM/MoarVM.git/archive/refs/tags/2026.01.zip",
          "type": "source-distribution"
        }
      ]
    },
    {
      "type": "library",
      "mime-type": "text/plain",
      "bom-ref": "pkg:raku/IO::Socket::Async::SSL?vers=vers:raku/%3E=0.8.0",
      "authors": [
        {
          "bom-ref": "JonathanWorthington",
          "name": "Jonathan Worthington"
        }
      ],
      "publisher": "zef",
      "group": "zef:raku-community-modules",
      "name": "IO::Socket::Async::SSL",
      "version": "0.8.2",
      "description": "Provides an API like IO::Socket::Async, but with TLS support",
      "scope": "required",
      "licenses": [
        {
          "license": {
            "id": "Artistic-2.0",
            "acknowledgement": "declared",
            "url": "https://spdx.org/licenses/Artistic-2.0.json"
          }
        }
      ],
      "purl": "pkg:raku/zef:raku-community-modules/IO::Socket::Async::SSL@0.8.2",
      "externalReferences": [
        {
          "url": "https://github.com/raku-community-modules/IO-Socket-Async-SSL",
          "type": "distribution"
        },
        {
          "url": "https://raku.land/zef:raku-community-modules/IO::Socket::Async::SSL?v=0.8.2",
          "type": "documentation"
        },
        {
          "url": "https://github.com/raku-community-modules/IO-Socket-Async-SSL/issues",
          "type": "issue-tracker"
        },
        {
          "url": "https://spdx.org/licenses/Artistic-2.0.json",
          "type": "license"
        },
        {
          "url": "https://github.com/raku-community-modules/IO-Socket-Async-SSL/archive/refs/tags/0.8.2.zip",
          "type": "source-distribution"
        }
      ],
      "tags": [
        "SSL",
        "TLS",
        "Asynchronous",
        "Socket"
      ]
    },
    {
      "type": "library",
      "mime-type": "text/plain",
      "bom-ref": "pkg:raku/OpenSSL",
      "authors": [
        {
          "bom-ref": "FilipSergot",
          "name": "Filip Sergot"
        },
        {
          "bom-ref": "ElizabethMattijsen",
          "name": "Elizabeth Mattijsen"
        }
      ],
      "publisher": "zef",
      "group": "zef:raku-community-modules",
      "name": "OpenSSL",
      "version": "0.2.6",
      "description": "OpenSSL bindings",
      "scope": "required",
      "licenses": [
        {
          "license": {
            "id": "MIT",
            "acknowledgement": "declared",
            "url": "https://spdx.org/licenses/MIT.json"
          }
        }
      ],
      "purl": "pkg:raku/zef:raku-community-modules/OpenSSL@0.2.6",
      "externalReferences": [
        {
          "url": "https://github.com/raku-community-modules/OpenSSL",
          "type": "distribution"
        },
        {
          "url": "https://raku.land/zef:raku-community-modules/OpenSSL?v=0.2.6",
          "type": "documentation"
        },
        {
          "url": "https://github.com/raku-community-modules/OpenSSL/issues",
          "type": "issue-tracker"
        },
        {
          "url": "https://spdx.org/licenses/MIT.json",
          "type": "license"
        },
        {
          "url": "https://github.com/raku-community-modules/OpenSSL/archive/refs/tags/0.2.6.zip",
          "type": "source-distribution"
        },
        {
          "url": "mailto:community@raku.org",
          "type": "support"
        }
      ],
      "tags": [
        "OPENSSL",
        "MD5",
        "SHA1",
        "SHA224",
        "SHA256",
        "SHA384",
        "SHA256"
      ]
    }
  ],
  "externalReferences": [
    {
      "url": "https://github.com/lizmat/IRC-Client",
      "type": "distribution"
    },
    {
      "url": "https://raku.land/zef:lizmat/IRC::Client?v=4.0.15",
      "type": "documentation"
    },
    {
      "url": "https://github.com/lizmat/IRC-Client/issues",
      "type": "issue-tracker"
    },
    {
      "url": "https://spdx.org/licenses/Artistic-2.0.json",
      "type": "license"
    },
    {
      "url": "https://github.com/lizmat/IRC-Client/archive/refs/tags/4.0.15.zip",
      "type": "source-distribution"
    },
    {
      "url": "mailto:liz@raku.rocks",
      "type": "support"
    }
  ],
  "dependencies": [
    {
      "ref": "Rakudo",
      "dependsOn": [
        "moar"
      ]
    },
    {
      "ref": "pkg:raku/IO::Socket::Async::SSL?vers=vers:raku/%3E=0.8.0",
      "dependsOn": [
        "pkg:raku/OpenSSL"
      ]
    },
    {
      "ref": "pkg:raku/zef:lizmat/SBOM::Raku@0.0.12",
      "dependsOn": [
        "Rakudo"
      ]
    }
  ]
}