{"tags":["UUID"],"test-depends":["Test","Test::When","Test::META"],"depends":["NativeCall","NativeLibs"],"description":"Perl 6 bindings for libuuid, for UUID generation","version":"0.4","license":"Artistic-2.0","provides":{"LibUUID":"lib/LibUUID.pm6"},"support":{"source":"https://github.com/CurtTilmes/perl6-libuuid.git","bugtracker":"https://github.com/CurtTilmes/perl6-libuuid/issues"},"authors":["Curt Tilmes <ctilmes@cpan.org>"],"name":"LibUUID","perl":"6.*","source-url":"https://github.com/CurtTilmes/perl6-libuuid.git","auth":"github:CurtTilmes"}