{"api":"0","auth":"cpan:TYIL","authors":["Patrick Spek <p.spek@tyil.work>"],"depends":[],"description":"Convenience functions for working with the XDG Base Directory Specification","dist":"IO::Path::XDG:ver<0.1.0>:auth<cpan:TYIL>","license":"AGPL-3.0","meta-version":0,"name":"IO::Path::XDG","perl":"6.d","provides":{"IO::Path::XDG":"lib/IO/Path/XDG.pm6"},"release-date":"2019-09-12","resources":[],"source-url":"https://raw.githubusercontent.com/raku/REA/main/archive/I/IO%3A%3APath%3A%3AXDG/IO%3A%3APath%3A%3AXDG%3Aver%3C0.1.0%3E%3Aauth%3Ccpan%3ATYIL%3E.tar.gz","tags":[],"version":"0.1.0"}