{
  "$schema": "http://cyclonedx.org/schema/bom-1.6.schema.json",
  "bomFormat": "CycloneDX",
  "specVersion": "1.6",
  "version": 1,
  "metadata": {
    "timestamp": "2025-08-08T19:38:38+00:00",
    "lifecycles": [
      {
        "phase": "pre-build"
      }
    ],
    "authors": [
      {
        "bom-ref": "SiavashAskariNasr",
        "name": "Siavash Askari Nasr"
      }
    ],
    "component": {
      "type": "library",
      "mime-type": "text/plain",
      "bom-ref": "pkg:raku/zef:CIAvash/Curry@0.1.2",
      "authors": [
        {
          "bom-ref": "SiavashAskariNasr",
          "name": "Siavash Askari Nasr"
        }
      ],
      "publisher": "zef",
      "group": "zef:CIAvash",
      "name": "Curry",
      "version": "0.1.2",
      "description": "Library for making curried functions.",
      "scope": "required",
      "hashes": [
        {
          "alg": "MD5",
          "content": "f5d3bc47a83b1de149cd47e0635d4de3"
        },
        {
          "alg": "SHA-1",
          "content": "ac829b354aa240d74013adc87572797b4c31f8f1"
        },
        {
          "alg": "SHA-256",
          "content": "71c000acb9391ec5ee2e55e943a8a3934147efda28c1e8271ee3faffbaa0ea32"
        },
        {
          "alg": "SHA-384",
          "content": "5d7e8d975973688091a59ce2d56af8a909c45d08ef5f26cc9185adcd87f8102aa036288b53c793059603318a08c63fbc"
        },
        {
          "alg": "SHA-512",
          "content": "ed2ff288769452f7007debdbffded0347a5f67940e20fb058912550c6ce18e389a23ed358df01c080b76c4c148821c162668fa74bbb7d39fde57c942514078b8"
        }
      ],
      "licenses": [
        {
          "license": {
            "id": "LGPL-3.0-or-later",
            "acknowledgement": "declared",
            "url": "https://spdx.org/licenses/LGPL-3.0-or-later.json"
          }
        }
      ],
      "purl": "pkg:raku/zef:CIAvash/Curry@0.1.2",
      "externalReferences": [
        {
          "url": "https://github.com/CIAvash/Curry",
          "type": "distribution"
        },
        {
          "url": "https://raku.land/zef:CIAvash/Curry?v=0.1.2",
          "type": "documentation"
        },
        {
          "url": "https://github.com/CIAvash/Curry/issues",
          "type": "issue-tracker"
        },
        {
          "url": "https://spdx.org/licenses/LGPL-3.0-or-later.json",
          "type": "license"
        },
        {
          "url": "https://github.com/CIAvash/Curry/archive/refs/tags/0.1.2.zip",
          "type": "source-distribution"
        }
      ],
      "tags": [
        "Curry",
        "Function",
        "Library",
        "Currying",
        "Functional Programming",
        "Curried",
        "Partial",
        "Trait"
      ]
    },
    "licenses": [
      {
        "license": {
          "id": "LGPL-3.0-or-later",
          "acknowledgement": "declared",
          "url": "https://spdx.org/licenses/LGPL-3.0-or-later.json"
        }
      }
    ],
    "tools": {
      "components": [
        {
          "type": "library",
          "mime-type": "text/plain",
          "bom-ref": "pkg:raku/zef:lizmat/SBOM::Raku@0.0.10",
          "authors": [
            {
              "bom-ref": "ElizabethMattijsen",
              "name": "Elizabeth Mattijsen"
            }
          ],
          "publisher": "zef",
          "group": "zef:lizmat",
          "name": "SBOM::Raku",
          "version": "0.0.10",
          "description": "Raku specific SBOM functionality",
          "scope": "required",
          "licenses": [
            {
              "license": {
                "id": "Artistic-2.0",
                "acknowledgement": "declared",
                "url": "https://spdx.org/licenses/Artistic-2.0.json"
              }
            }
          ],
          "purl": "pkg:raku/zef:lizmat/SBOM::Raku@0.0.10",
          "externalReferences": [
            {
              "url": "https://github.com/lizmat/SBOM-Raku",
              "type": "distribution"
            },
            {
              "url": "https://raku.land/zef:lizmat/SBOM::Raku?v=0.0.10",
              "type": "documentation"
            },
            {
              "url": "https://github.com/lizmat/SBOM-Raku/issues",
              "type": "issue-tracker"
            },
            {
              "url": "https://spdx.org/licenses/Artistic-2.0.json",
              "type": "license"
            },
            {
              "url": "https://github.com/lizmat/SBOM-Raku/archive/refs/tags/0.0.10.zip",
              "type": "source-distribution"
            },
            {
              "url": "mailto:liz@raku.rocks",
              "type": "support"
            }
          ],
          "tags": [
            "SBOM",
            "RAKU",
            "META"
          ]
        }
      ]
    }
  },
  "components": [
    {
      "type": "platform",
      "bom-ref": "Rakudo",
      "authors": [
        {
          "bom-ref": "RakudoCoreDevelopers",
          "name": "Rakudo Core Developers"
        }
      ],
      "publisher": "Rakudo Core Developers",
      "group": "Rakudo Core Developers",
      "name": "Rakudo",
      "version": "2025.06.1-12-g3aea31ed1",
      "description": "The Rakudo™ Compiler implementing the Raku® Programming Language",
      "scope": "required",
      "licenses": [
        {
          "license": {
            "id": "Artistic-2.0",
            "acknowledgement": "declared",
            "url": "https://spdx.org/licenses/Artistic-2.0.json"
          }
        }
      ],
      "copyright": "© 2006 - 2025 Yet Another Society",
      "externalReferences": [
        {
          "url": "https://github.com/rakudo/rakudo",
          "type": "distribution"
        },
        {
          "url": "https://github.com/rakudo/rakudo/issues",
          "type": "issue-tracker"
        },
        {
          "url": "https://github.com/rakudo/rakudo/archive/3aea31ed1.zip",
          "type": "source-distribution"
        },
        {
          "url": "irc://libera.chat/raku",
          "type": "chat"
        }
      ]
    },
    {
      "type": "platform",
      "bom-ref": "moar",
      "authors": [
        {
          "bom-ref": "TheMoarVMTeam",
          "name": "The MoarVM Team"
        }
      ],
      "publisher": "The MoarVM Team",
      "group": "The MoarVM Team",
      "name": "Moar",
      "version": "2025.06-5-gb1c74b8d8",
      "description": "Short for \"Metamodel On A Runtime\", MoarVM is a modern virtual machine built for the Rakudo compiler and the NQP Compiler Toolchain.",
      "scope": "required",
      "licenses": [
        {
          "license": {
            "id": "Artistic-2.0",
            "acknowledgement": "declared",
            "url": "https://spdx.org/licenses/Artistic-2.0.json"
          }
        }
      ],
      "copyright": "© 2012 - 2025 Jonathan Worthington",
      "externalReferences": [
        {
          "url": "https://github.com/MoarVM/MoarVM",
          "type": "distribution"
        },
        {
          "url": "https://github.com/MoarVM/MoarVM/issues",
          "type": "issue-tracker"
        },
        {
          "url": "irc://libera.chat/moarvm",
          "type": "chat"
        },
        {
          "url": "https://github.com/MoarVM/MoarVM.git/archive/refs/tags/b1c74b8d8.zip",
          "type": "source-distribution"
        }
      ]
    }
  ],
  "externalReferences": [
    {
      "url": "https://github.com/CIAvash/Curry",
      "type": "distribution"
    },
    {
      "url": "https://raku.land/zef:CIAvash/Curry?v=0.1.2",
      "type": "documentation"
    },
    {
      "url": "https://github.com/CIAvash/Curry/issues",
      "type": "issue-tracker"
    },
    {
      "url": "https://spdx.org/licenses/LGPL-3.0-or-later.json",
      "type": "license"
    },
    {
      "url": "https://github.com/CIAvash/Curry/archive/refs/tags/0.1.2.zip",
      "type": "source-distribution"
    }
  ],
  "dependencies": [
    {
      "ref": "Rakudo",
      "dependsOn": [
        "moar"
      ]
    },
    {
      "ref": "pkg:raku/zef:lizmat/SBOM::Raku@0.0.10",
      "dependsOn": [
        "Rakudo"
      ]
    }
  ]
}